setup.py
arabicstemmer/__init__.py
arabicstemmer/among.py
arabicstemmer/arabic_stemmer.py
arabicstemmer/basestemmer.py
arabicstemmer.egg-info/PKG-INFO
arabicstemmer.egg-info/SOURCES.txt
arabicstemmer.egg-info/dependency_links.txt
arabicstemmer.egg-info/top_level.txt