Metadata-Version: 1.0
Name: arabicstemmer
Version: 0.2
Summary: A snowball-based stemming algorithm for Arabic aimed mainly to improve search.
Home-page: http://www.arabicstemmer.com/
Author: Assem Chelli
Author-email: assem.ch@gmail.com
License: BSD
Platform: UNKNOWN
